skpoly/__init__.py
skpoly/_base.py
skpoly/_bernstein.py
skpoly/_legendre.py
skpoly-0.1.2.dist-info/METADATA
skpoly-0.1.2.dist-info/WHEEL
skpoly-0.1.2.dist-info/licenses/LICENSE
skpoly-0.1.2.dist-info/RECORD
