Metadata-Version: 2.4
Name: skpoly
Version: 0.1.2
Summary: Polynomial basis transformers for scikit-learn.
Project-URL: Homepage, https://github.com/axshtoff/skpoly
Project-URL: Repository, https://github.com/axshtoff/skpoly
Project-URL: Bug Tracker, https://github.com/axshtoff/skpoly/issues
Author: Alex Shtoff
License: MIT
License-File: LICENSE
Keywords: feature-engineering,machine-learning,polynomials,scikit-learn
Classifier: Development Status :: 3 - Alpha
Classifier: Intended Audience :: Developers
Classifier: License :: OSI Approved :: MIT License
Classifier: Programming Language :: Python
Classifier: Programming Language :: Python :: 3
Classifier: Programming Language :: Python :: 3.10
Classifier: Topic :: Scientific/Engineering :: Artificial Intelligence
Requires-Python: >=3.10
Requires-Dist: numpy>=1.24
Requires-Dist: scikit-learn>=1.3
Requires-Dist: scipy>=1.10
